kegbot_kegboard2-1.1.5-py2.7-nspkg.pth
kegbot/kegboard/__init__.py
kegbot/kegboard/crc16.py
kegbot/kegboard/crc16_test.py
kegbot/kegboard/exceptions.py
kegbot/kegboard/kegboard.py
kegbot/kegboard/kegboard_test.py
kegbot/kegboard/message.py
kegbot_kegboard2-1.1.5.data/scripts/distribute_setup.py
kegbot_kegboard2-1.1.5.data/scripts/kegboard-info.py
kegbot_kegboard2-1.1.5.data/scripts/kegboard-monitor.py
kegbot_kegboard2-1.1.5.data/scripts/kegboard-tester.py
kegbot_kegboard2-1.1.5.data/scripts/set-kegboard-serialnumber
kegbot_kegboard2-1.1.5.dist-info/DESCRIPTION.rst
kegbot_kegboard2-1.1.5.dist-info/METADATA
kegbot_kegboard2-1.1.5.dist-info/RECORD
kegbot_kegboard2-1.1.5.dist-info/WHEEL
kegbot_kegboard2-1.1.5.dist-info/metadata.json
kegbot_kegboard2-1.1.5.dist-info/namespace_packages.txt
kegbot_kegboard2-1.1.5.dist-info/top_level.txt
