Metadata-Version: 2.0
Name: kegbot-kegboard2
Version: 1.1.5
Summary: Kegboard support library.
Home-page: http://kegbot.org/
Author: mike wakerly (updated by dandrzej80)
Author-email: opensource@hoho.com
License: UNKNOWN
Platform: UNKNOWN
Requires-Dist: kegbot-pyutils (>=0.1.2)
Requires-Dist: python-gflags
Requires-Dist: pyserial
